discord_andshrew/__init__.py
discord_andshrew/discord.py
discord_andshrew/message.py
discord_andshrew/queue.py
discord_andshrew-0.1.0.dist-info/METADATA
discord_andshrew-0.1.0.dist-info/WHEEL
discord_andshrew-0.1.0.dist-info/licenses/LICENSE
discord_andshrew-0.1.0.dist-info/RECORD
