Metadata-Version: 2.3
Name: discord_andshrew
Version: 0.1.0
Summary: A simple package for building, sending and queuing Discord webhook messages
Project-URL: Homepage, https://github.com/andshrew/Discord-Message-Python
Project-URL: Bug Tracker, https://github.com/andshrew/Discord-Message-Python/issues
Author-email: andshrew <7409326+andshrew@users.noreply.github.com>
License-File: LICENSE
Classifier: License :: OSI Approved :: MIT License
Classifier: Operating System :: OS Independent
Classifier: Programming Language :: Python :: 3
Requires-Python: >=3.8
Requires-Dist: requests>=2.31
